{
  "olpVersion" : "0.1",

  "paths" : [
    {
      "name" : "OWASP-Top-10",
      "title" : "OWASP Top 10",
      "description" : "This course focuses on the most common security defects identified by the Open Web Application Security Project (OWASP)",
      "privacy" : "public",
      "pages" : [
        {"page" : "./codiscope-owasp-top-10/pages/welcome.md"},
        {"module" : "OWASP-Top-10-screenshots"},
        {"module" : "OWASP-Top-10-flash"},
        {"page" : "./codiscope-owasp-top-10/pages/live-long.md"}
      ]
    }
  ],

  "modules" : [
    {
      "olm" : "./codiscope-owasp-top-10/modules/welcome.md"
    },
    {
      "olm" : "./codiscope-owasp-top-10/modules/flash.md"
    },
    {
      "olm" : "./simon-bailey/test-angularjs-directive.md"
    },
    {
      "olm" : "./yext/orientation.md"
    }
  ],

  "assets" : [
  ]
}
